{
    "players": [
        {
            "team": "canucks",
            "sweater-number-": "33",
            "position": "C",
            "player-name": "Henrik Sedin",
            "games-played": "70",
            "goals": "11",
            "assists": "39",
            "points": "50",
            "plus/minus-": "3",
            "penalties-in-minutes": "42",
            "power-play-goals": "4",
            "shorthanded-goals": "0",
            "game-winning-goals": "1",
            "shots-on-goal": "97",
            "shooting-percentage": "11.30"
        },
        {
            "team": "canucks",
            "sweater-number-": "22",
            "position": "L",
            "player-name": "Daniel Sedin",
            "games-played": "73",
            "goals": "16",
            "assists": "31",
            "points": "47",
            "plus/minus-": "0",
            "penalties-in-minutes": "38",
            "power-play-goals": "5",
            "shorthanded-goals": "0",
            "game-winning-goals": "4",
            "shots-on-goal": "224",
            "shooting-percentage": "7.10"
        },
        {
            "team": "canucks",
            "sweater-number-": "20",
            "position": "L",
            "player-name": "Chris Higgins",
            "games-played": "78",
            "goals": "17",
            "assists": "22",
            "points": "39",
            "plus/minus-": "-14",
            "penalties-in-minutes": "30",
            "power-play-goals": "2",
            "shorthanded-goals": "0",
            "game-winning-goals": "4",
            "shots-on-goal": "216",
            "shooting-percentage": "7.90"
        },
        {
            "team": "canucks",
            "sweater-number-": "9",
            "position": "R",
            "player-name": "Zack Kassian",
            "games-played": "73",
            "goals": "14",
            "assists": "15",
            "points": "29",
            "plus/minus-": "-4",
            "penalties-in-minutes": "124",
            "power-play-goals": "1",
            "shorthanded-goals": "0",
            "game-winning-goals": "2",
            "shots-on-goal": "91",
            "shooting-percentage": "15.40"
        },
        {
            "team": "canucks",
            "sweater-number-": "3",
            "position": "D",
            "player-name": "Kevin Bieksa",
            "games-played": "76",
            "goals": "4",
            "assists": "20",
            "points": "24",
            "plus/minus-": "-8",
            "penalties-in-minutes": "104",
            "power-play-goals": "1",
            "shorthanded-goals": "0",
            "game-winning-goals": "1",
            "shots-on-goal": "167",
            "shooting-percentage": "2.40"
        },
        {
            "team": "canucks",
            "sweater-number-": "15",
            "position": "R",
            "player-name": "Brad Richardson",
            "games-played": "73",
            "goals": "11",
            "assists": "12",
            "points": "23",
            "plus/minus-": "1",
            "penalties-in-minutes": "39",
            "power-play-goals": "1",
            "shorthanded-goals": "2",
            "game-winning-goals": "2",
            "shots-on-goal": "85",
            "shooting-percentage": "12.90"
        },
        {
            "team": "canucks",
            "sweater-number-": "2",
            "position": "D",
            "player-name": "Dan Hamhuis",
            "games-played": "79",
            "goals": "5",
            "assists": "17",
            "points": "22",
            "plus/minus-": "13",
            "penalties-in-minutes": "26",
            "power-play-goals": "0",
            "shorthanded-goals": "0",
            "game-winning-goals": "0",
            "shots-on-goal": "150",
            "shooting-percentage": "3.30"
        },
        {
            "team": "canucks",
            "sweater-number-": "23",
            "position": "D",
            "player-name": "Alexander Edler",
            "games-played": "63",
            "goals": "7",
            "assists": "15",
            "points": "22",
            "plus/minus-": "-39",
            "penalties-in-minutes": "50",
            "power-play-goals": "4",
            "shorthanded-goals": "0",
            "game-winning-goals": "0",
            "shots-on-goal": "178",
            "shooting-percentage": "3.90"
        },
        {
            "team": "canucks",
            "sweater-number-": "36",
            "position": "R",
            "player-name": "Jannik Hansen",
            "games-played": "71",
            "goals": "11",
            "assists": "9",
            "points": "20",
            "plus/minus-": "-9",
            "penalties-in-minutes": "43",
            "power-play-goals": "0",
            "shorthanded-goals": "1",
            "game-winning-goals": "3",
            "shots-on-goal": "112",
            "shooting-percentage": "9.80"
        },
        {
            "team": "canucks",
            "sweater-number-": "8",
            "position": "D",
            "player-name": "Christopher Tanev",
            "games-played": "64",
            "goals": "6",
            "assists": "11",
            "points": "17",
            "plus/minus-": "12",
            "penalties-in-minutes": "8",
            "power-play-goals": "0",
            "shorthanded-goals": "1",
            "game-winning-goals": "2",
            "shots-on-goal": "65",
            "shooting-percentage": "9.20"
        },
        {
            "team": "canucks",
            "sweater-number-": "18",
            "position": "D",
            "player-name": "Ryan Stanton",
            "games-played": "64",
            "goals": "1",
            "assists": "15",
            "points": "16",
            "plus/minus-": "5",
            "penalties-in-minutes": "32",
            "power-play-goals": "0",
            "shorthanded-goals": "0",
            "game-winning-goals": "0",
            "shots-on-goal": "65",
            "shooting-percentage": "1.50"
        },
        {
            "team": "canucks",
            "sweater-number-": "14",
            "position": "R",
            "player-name": "Alexandre Burrows",
            "games-played": "49",
            "goals": "5",
            "assists": "10",
            "points": "15",
            "plus/minus-": "-9",
            "penalties-in-minutes": "71",
            "power-play-goals": "2",
            "shorthanded-goals": "0",
            "game-winning-goals": "0",
            "shots-on-goal": "104",
            "shooting-percentage": "4.80"
        },
        {
            "team": "canucks",
            "sweater-number-": "6",
            "position": "D",
            "player-name": "Yannick Weber",
            "games-played": "49",
            "goals": "6",
            "assists": "4",
            "points": "10",
            "plus/minus-": "-7",
            "penalties-in-minutes": "16",
            "power-play-goals": "3",
            "shorthanded-goals": "0",
            "game-winning-goals": "2",
            "shots-on-goal": "70",
            "shooting-percentage": "8.60"
        },
        {
            "team": "canucks",
            "sweater-number-": "29",
            "position": "L",
            "player-name": "Tom Sestito",
            "games-played": "77",
            "goals": "5",
            "assists": "4",
            "points": "9",
            "plus/minus-": "-14",
            "penalties-in-minutes": "213",
            "power-play-goals": "1",
            "shorthanded-goals": "0",
            "game-winning-goals": "0",
            "shots-on-goal": "31",
            "shooting-percentage": "16.10"
        },
        {
            "team": "canucks",
            "sweater-number-": "27",
            "position": "C",
            "player-name": "Shawn Matthias",
            "games-played": "18",
            "goals": "3",
            "assists": "4",
            "points": "7",
            "plus/minus-": "-3",
            "penalties-in-minutes": "12",
            "power-play-goals": "0",
            "shorthanded-goals": "0",
            "game-winning-goals": "0",
            "shots-on-goal": "39",
            "shooting-percentage": "7.70"
        },
        {
            "team": "canucks",
            "sweater-number-": "46",
            "position": "R",
            "player-name": "Nicklas Jensen",
            "games-played": "17",
            "goals": "3",
            "assists": "3",
            "points": "6",
            "plus/minus-": "-1",
            "penalties-in-minutes": "10",
            "power-play-goals": "0",
            "shorthanded-goals": "0",
            "game-winning-goals": "1",
            "shots-on-goal": "30",
            "shooting-percentage": "10.00"
        },
        {
            "team": "canucks",
            "sweater-number-": "49",
            "position": "R",
            "player-name": "Darren Archibald",
            "games-played": "16",
            "goals": "1",
            "assists": "2",
            "points": "3",
            "plus/minus-": "1",
            "penalties-in-minutes": "0",
            "power-play-goals": "0",
            "shorthanded-goals": "0",
            "game-winning-goals": "0",
            "shots-on-goal": "11",
            "shooting-percentage": "9.10"
        },
        {
            "team": "canucks",
            "sweater-number-": "26",
            "position": "D",
            "player-name": "Frank Corrado",
            "games-played": "15",
            "goals": "1",
            "assists": "0",
            "points": "1",
            "plus/minus-": "-2",
            "penalties-in-minutes": "4",
            "power-play-goals": "0",
            "shorthanded-goals": "0",
            "game-winning-goals": "0",
            "shots-on-goal": "20",
            "shooting-percentage": "5.00"
        },
        {
            "team": "canucks",
            "sweater-number-": "54",
            "position": "C",
            "player-name": "Kellan Lain",
            "games-played": "9",
            "goals": "1",
            "assists": "0",
            "points": "1",
            "plus/minus-": "1",
            "penalties-in-minutes": "21",
            "power-play-goals": "0",
            "shorthanded-goals": "0",
            "game-winning-goals": "0",
            "shots-on-goal": "7",
            "shooting-percentage": "14.30"
        },
        {
            "team": "canucks",
            "sweater-number-": "40",
            "position": "L",
            "player-name": "Michael Zalewski",
            "games-played": "2",
            "goals": "0",
            "assists": "1",
            "points": "1",
            "plus/minus-": "2",
            "penalties-in-minutes": "0",
            "power-play-goals": "0",
            "shorthanded-goals": "0",
            "game-winning-goals": "0",
            "shots-on-goal": "2",
            "shooting-percentage": "0.00"
        },
        {
            "team": "canucks",
            "sweater-number-": "33",
            "position": "C",
            "player-name": "Henrik Sedin",
            "games-played": "70",
            "goals": "11",
            "assists": "39",
            "points": "50",
            "plus/minus-": "3",
            "penalties-in-minutes": "42",
            "power-play-goals": "4",
            "shorthanded-goals": "0",
            "game-winning-goals": "1",
            "shots-on-goal": "97",
            "shooting-percentage": "11.30"
        },
        {
            "team": "canucks",
            "sweater-number-": "22",
            "position": "L",
            "player-name": "Daniel Sedin",
            "games-played": "73",
            "goals": "16",
            "assists": "31",
            "points": "47",
            "plus/minus-": "0",
            "penalties-in-minutes": "38",
            "power-play-goals": "5",
            "shorthanded-goals": "0",
            "game-winning-goals": "4",
            "shots-on-goal": "224",
            "shooting-percentage": "7.10"
        },
        {
            "team": "canucks",
            "sweater-number-": "20",
            "position": "L",
            "player-name": "Chris Higgins",
            "games-played": "78",
            "goals": "17",
            "assists": "22",
            "points": "39",
            "plus/minus-": "-14",
            "penalties-in-minutes": "30",
            "power-play-goals": "2",
            "shorthanded-goals": "0",
            "game-winning-goals": "4",
            "shots-on-goal": "216",
            "shooting-percentage": "7.90"
        },
        {
            "team": "canucks",
            "sweater-number-": "9",
            "position": "R",
            "player-name": "Zack Kassian",
            "games-played": "73",
            "goals": "14",
            "assists": "15",
            "points": "29",
            "plus/minus-": "-4",
            "penalties-in-minutes": "124",
            "power-play-goals": "1",
            "shorthanded-goals": "0",
            "game-winning-goals": "2",
            "shots-on-goal": "91",
            "shooting-percentage": "15.40"
        },
        {
            "team": "canucks",
            "sweater-number-": "3",
            "position": "D",
            "player-name": "Kevin Bieksa",
            "games-played": "76",
            "goals": "4",
            "assists": "20",
            "points": "24",
            "plus/minus-": "-8",
            "penalties-in-minutes": "104",
            "power-play-goals": "1",
            "shorthanded-goals": "0",
            "game-winning-goals": "1",
            "shots-on-goal": "167",
            "shooting-percentage": "2.40"
        },
        {
            "team": "canucks",
            "sweater-number-": "15",
            "position": "R",
            "player-name": "Brad Richardson",
            "games-played": "73",
            "goals": "11",
            "assists": "12",
            "points": "23",
            "plus/minus-": "1",
            "penalties-in-minutes": "39",
            "power-play-goals": "1",
            "shorthanded-goals": "2",
            "game-winning-goals": "2",
            "shots-on-goal": "85",
            "shooting-percentage": "12.90"
        },
        {
            "team": "canucks",
            "sweater-number-": "2",
            "position": "D",
            "player-name": "Dan Hamhuis",
            "games-played": "79",
            "goals": "5",
            "assists": "17",
            "points": "22",
            "plus/minus-": "13",
            "penalties-in-minutes": "26",
            "power-play-goals": "0",
            "shorthanded-goals": "0",
            "game-winning-goals": "0",
            "shots-on-goal": "150",
            "shooting-percentage": "3.30"
        },
        {
            "team": "canucks",
            "sweater-number-": "23",
            "position": "D",
            "player-name": "Alexander Edler",
            "games-played": "63",
            "goals": "7",
            "assists": "15",
            "points": "22",
            "plus/minus-": "-39",
            "penalties-in-minutes": "50",
            "power-play-goals": "4",
            "shorthanded-goals": "0",
            "game-winning-goals": "0",
            "shots-on-goal": "178",
            "shooting-percentage": "3.90"
        },
        {
            "team": "canucks",
            "sweater-number-": "36",
            "position": "R",
            "player-name": "Jannik Hansen",
            "games-played": "71",
            "goals": "11",
            "assists": "9",
            "points": "20",
            "plus/minus-": "-9",
            "penalties-in-minutes": "43",
            "power-play-goals": "0",
            "shorthanded-goals": "1",
            "game-winning-goals": "3",
            "shots-on-goal": "112",
            "shooting-percentage": "9.80"
        },
        {
            "team": "canucks",
            "sweater-number-": "8",
            "position": "D",
            "player-name": "Christopher Tanev",
            "games-played": "64",
            "goals": "6",
            "assists": "11",
            "points": "17",
            "plus/minus-": "12",
            "penalties-in-minutes": "8",
            "power-play-goals": "0",
            "shorthanded-goals": "1",
            "game-winning-goals": "2",
            "shots-on-goal": "65",
            "shooting-percentage": "9.20"
        },
        {
            "team": "canucks",
            "sweater-number-": "18",
            "position": "D",
            "player-name": "Ryan Stanton",
            "games-played": "64",
            "goals": "1",
            "assists": "15",
            "points": "16",
            "plus/minus-": "5",
            "penalties-in-minutes": "32",
            "power-play-goals": "0",
            "shorthanded-goals": "0",
            "game-winning-goals": "0",
            "shots-on-goal": "65",
            "shooting-percentage": "1.50"
        },
        {
            "team": "canucks",
            "sweater-number-": "14",
            "position": "R",
            "player-name": "Alexandre Burrows",
            "games-played": "49",
            "goals": "5",
            "assists": "10",
            "points": "15",
            "plus/minus-": "-9",
            "penalties-in-minutes": "71",
            "power-play-goals": "2",
            "shorthanded-goals": "0",
            "game-winning-goals": "0",
            "shots-on-goal": "104",
            "shooting-percentage": "4.80"
        },
        {
            "team": "canucks",
            "sweater-number-": "6",
            "position": "D",
            "player-name": "Yannick Weber",
            "games-played": "49",
            "goals": "6",
            "assists": "4",
            "points": "10",
            "plus/minus-": "-7",
            "penalties-in-minutes": "16",
            "power-play-goals": "3",
            "shorthanded-goals": "0",
            "game-winning-goals": "2",
            "shots-on-goal": "70",
            "shooting-percentage": "8.60"
        },
        {
            "team": "canucks",
            "sweater-number-": "29",
            "position": "L",
            "player-name": "Tom Sestito",
            "games-played": "77",
            "goals": "5",
            "assists": "4",
            "points": "9",
            "plus/minus-": "-14",
            "penalties-in-minutes": "213",
            "power-play-goals": "1",
            "shorthanded-goals": "0",
            "game-winning-goals": "0",
            "shots-on-goal": "31",
            "shooting-percentage": "16.10"
        },
        {
            "team": "canucks",
            "sweater-number-": "27",
            "position": "C",
            "player-name": "Shawn Matthias",
            "games-played": "18",
            "goals": "3",
            "assists": "4",
            "points": "7",
            "plus/minus-": "-3",
            "penalties-in-minutes": "12",
            "power-play-goals": "0",
            "shorthanded-goals": "0",
            "game-winning-goals": "0",
            "shots-on-goal": "39",
            "shooting-percentage": "7.70"
        },
        {
            "team": "canucks",
            "sweater-number-": "46",
            "position": "R",
            "player-name": "Nicklas Jensen",
            "games-played": "17",
            "goals": "3",
            "assists": "3",
            "points": "6",
            "plus/minus-": "-1",
            "penalties-in-minutes": "10",
            "power-play-goals": "0",
            "shorthanded-goals": "0",
            "game-winning-goals": "1",
            "shots-on-goal": "30",
            "shooting-percentage": "10.00"
        },
        {
            "team": "canucks",
            "sweater-number-": "49",
            "position": "R",
            "player-name": "Darren Archibald",
            "games-played": "16",
            "goals": "1",
            "assists": "2",
            "points": "3",
            "plus/minus-": "1",
            "penalties-in-minutes": "0",
            "power-play-goals": "0",
            "shorthanded-goals": "0",
            "game-winning-goals": "0",
            "shots-on-goal": "11",
            "shooting-percentage": "9.10"
        },
        {
            "team": "canucks",
            "sweater-number-": "26",
            "position": "D",
            "player-name": "Frank Corrado",
            "games-played": "15",
            "goals": "1",
            "assists": "0",
            "points": "1",
            "plus/minus-": "-2",
            "penalties-in-minutes": "4",
            "power-play-goals": "0",
            "shorthanded-goals": "0",
            "game-winning-goals": "0",
            "shots-on-goal": "20",
            "shooting-percentage": "5.00"
        },
        {
            "team": "canucks",
            "sweater-number-": "54",
            "position": "C",
            "player-name": "Kellan Lain",
            "games-played": "9",
            "goals": "1",
            "assists": "0",
            "points": "1",
            "plus/minus-": "1",
            "penalties-in-minutes": "21",
            "power-play-goals": "0",
            "shorthanded-goals": "0",
            "game-winning-goals": "0",
            "shots-on-goal": "7",
            "shooting-percentage": "14.30"
        },
        {
            "team": "canucks",
            "sweater-number-": "40",
            "position": "L",
            "player-name": "Michael Zalewski",
            "games-played": "2",
            "goals": "0",
            "assists": "1",
            "points": "1",
            "plus/minus-": "2",
            "penalties-in-minutes": "0",
            "power-play-goals": "0",
            "shorthanded-goals": "0",
            "game-winning-goals": "0",
            "shots-on-goal": "2",
            "shooting-percentage": "0.00"
        }
    ]
}